bin/draco_decoder
bin/draco_decoder-1.5.7
bin/draco_encoder
bin/draco_encoder-1.5.7
include/draco/animation/keyframe_animation.h
include/draco/animation/keyframe_animation_decoder.h
include/draco/animation/keyframe_animation_encoder.h
include/draco/attributes/attribute_octahedron_transform.h
include/draco/attributes/attribute_quantization_transform.h
include/draco/attributes/attribute_transform.h
include/draco/attributes/attribute_transform_data.h
include/draco/attributes/attribute_transform_type.h
include/draco/attributes/geometry_attribute.h
include/draco/attributes/geometry_indices.h
include/draco/attributes/point_attribute.h
include/draco/compression/attributes/attributes_decoder.h
include/draco/compression/attributes/attributes_decoder_interface.h
include/draco/compression/attributes/attributes_encoder.h
include/draco/compression/attributes/kd_tree_attributes_decoder.h
include/draco/compression/attributes/kd_tree_attributes_encoder.h
include/draco/compression/attributes/kd_tree_attributes_shared.h
include/draco/compression/attributes/linear_sequencer.h
include/draco/compression/attributes/mesh_attribute_indices_encoding_data.h
include/draco/compression/attributes/normal_compression_utils.h
include/draco/compression/attributes/point_d_vector.h
include/draco/compression/attributes/points_sequencer.h
include/draco/compression/attributes/prediction_schemes/mesh_prediction_scheme_constrained_multi_parallelogram_decoder.h
include/draco/compression/attributes/prediction_schemes/mesh_prediction_scheme_constrained_multi_parallelogram_encoder.h
include/draco/compression/attributes/prediction_schemes/mesh_prediction_scheme_constrained_multi_parallelogram_shared.h
include/draco/compression/attributes/prediction_schemes/mesh_prediction_scheme_data.h
include/draco/compression/attributes/prediction_schemes/mesh_prediction_scheme_decoder.h
include/draco/compression/attributes/prediction_schemes/mesh_prediction_scheme_encoder.h
py3dm-0.1.0.dist-info/METADATA
py3dm-0.1.0.dist-info/WHEEL
py3dm-0.1.0.dist-info/licenses/LICENSE
py3dm-0.1.0.dist-info/RECORD
