Metadata-Version: 2.2
Name: py3dm
Version: 0.1.0
Summary: Python bindings for openNURBS using nanobind.
Author-Email: Studio W Engineers <studio.w.engineers@gmail.com>
Classifier: Intended Audience :: Developers
Classifier: License :: OSI Approved :: BSD License
Classifier: Programming Language :: C++
Classifier: Programming Language :: Python :: 3 :: Only
Classifier: Programming Language :: Python :: 3.12
Classifier: Programming Language :: Python :: 3.13
Classifier: Programming Language :: Python :: 3.14
Classifier: Programming Language :: Python :: Implementation :: CPython
Classifier: Topic :: Software Development :: Libraries :: Python Modules
Classifier: Topic :: Utilities
Project-URL: Homepage, https://github.com/StudioWEngineers/py3dm
Requires-Python: >=3.12
